pyxgram/__init__.py
pyxgram/bot.py
pyxgram/include.py
pyxgram-2.1.dist-info/LICENSE.txt
pyxgram-2.1.dist-info/METADATA
pyxgram-2.1.dist-info/WHEEL
pyxgram-2.1.dist-info/top_level.txt
pyxgram-2.1.dist-info/RECORD
