Metadata-Version: 2.1
Name: pyxgram
Version: 2.1
Summary: A framework for python bots for telegram
Home-page: https://github.com/borisd93/pyxgram
Author: Boris Daniel Martinez Millan
Author-email: edkz@nogafam.me
License: UNKNOWN
Project-URL: Bug Tracker, https://github.com/borisd93/pyxgram/issues
Keywords: Telegram,Bot
Platform: UNKNOWN
Classifier: Programming Language :: Python :: 3
Classifier: License :: OSI Approved :: GNU General Public License v3 (GPLv3)
Classifier: Development Status :: 5 - Production/Stable
Requires-Python: >=3.6
